tpy/__init__.py
tpy/__version__.py
tpy/cli.py
tpy/tmux.py
tpy/utils.py
tpy-0.3.0.dist-info/LICENSE
tpy-0.3.0.dist-info/METADATA
tpy-0.3.0.dist-info/WHEEL
tpy-0.3.0.dist-info/entry_points.txt
tpy-0.3.0.dist-info/top_level.txt
tpy-0.3.0.dist-info/RECORD
